Workbook

Sheet Matriz de pruebas
A1: Entregable 4. Evidencia de pruebas - Pulpería Tulita
A2: Versión probada: v0.1.0 (prototipo Android) | Entorno: emulador Medium_Phone_API_37.0 y teléfono Android | Flutter 3.47.7
A3: Resultados registrados por el equipo (Fernando, 11/10/2026) a partir de las pruebas ejecutadas. Las celdas AMARILLAS contienen datos que todavía deben completarse (tiempos, medidas). En Evidencia figura el nombre del archivo que debe existir en docs/evidencias/. Estado: Aprobado, Fallido, Pendiente o No aplica.
A5: ID | B5: Tipo | C5: Requisito | D5: Descripción de la prueba | E5: Datos utilizados | F5: Resultado esperado | G5: Resultado obtenido | H5: Evidencia | I5: Estado | J5: Responsable / fecha
A6: PRU-01 | B6: Positiva | C6: RF-01, RF-02, RF-08 | D6: Agregar un producto válido y ver su precio de venta | E6: Nombre: Aceite 500ml | Categoría: Abarrotes | Costo: 50.00 | Stock: 10 | F6: El producto aparece en la lista con Ganancia (20%) 10,00 C$ y PRECIO DE VENTA 60,00 C$; se muestra '¡Producto guardado!'. | G6: Aparece Aceite 500ml, stock 10, costo 50,00 C$, ganancia 10,00 C$ y precio de venta 60,00 C$. | H6: Captura de la lista de inventario (11/10/2026) | I6: Aprobado | J6: Fernando, 11/10/2026
A7: PRU-02 | B7: Positiva | C7: RF-02, RF-08 | D7: Agregar un segundo producto con decimales | E7: Nombre: Arroz 1lb | Categoría: Granos básicos | Costo: 18.50 | Stock: 25 | F7: Ganancia 3,70 C$ y precio de venta 22,20 C$. | G7: Costo 18,50 C$, ganancia 3,70 C$, precio de venta 22,20 C$, stock 25. | H7: Captura de la lista de inventario (11/10/2026) | I7: Aprobado | J7: Fernando, 11/10/2026
A8: PRU-03 | B8: Positiva | C8: RF-02, RF-08 | D8: Agregar un tercer producto de otra categoría | E8: Nombre: Jabon para lavar platos | Categoría: Limpieza e higiene | Costo: 15.00 | Stock: 50 | F8: Ganancia 3,00 C$ y precio de venta 18,00 C$. | G8: Costo 15,00 C$, ganancia 3,00 C$, precio de venta 18,00 C$, stock 50. | H8: Captura de la búsqueda 'Jab' (11/10/2026) | I8: Aprobado | J8: Fernando, 11/10/2026
A9: PRU-04 | B9: Positiva | C9: RF-02, RNF-02 | D9: Costo escrito con coma decimal | E9: Costo: 12,50 (con coma) | demás campos válidos | F9: Se acepta y se interpreta como 12.50; precio de venta 15,00 C$. | G9: Con 12,50 el producto se guardó y el precio de venta fue 15,00 C$. | H9: evidencias/PRU-04.png | I9: Aprobado | J9: Fernando, 11/10/2026
A10: PRU-05 | B10: Positiva | C10: RF-08 | D10: Vista previa del precio mientras se escribe el costo | E10: Escribir 50 en 'Costo de compra'; luego borrar el campo | F10: Con 50 muestra 60,00 C$ en 'Precio de venta (+20%)'; con el campo vacío muestra '—'. | G10: Al escribir 50 se mostró 60,00 C$; con el campo vacío se mostró '—'. | H10: evidencias/PRU-05.png | I10: Aprobado | J10: Fernando, 11/10/2026
A11: PRU-06 | B11: Positiva | C11: RNF-01 | D11: Persistencia al cerrar y volver a abrir la app | E11: Productos ya registrados; cerrar la app por completo y reabrir | F11: Los productos siguen en la lista con los mismos datos. | G11: Después de reiniciar la app, el producto Aceite 500ml seguía en la lista. | H11: Captura de la lista tras reiniciar (11/10/2026) | I11: Aprobado | J11: Fernando, 11/10/2026
A12: PRU-07 | B12: Positiva | C12: RF-04 | D12: Buscar por nombre | E12: Texto de búsqueda: Jab | F12: Solo se muestra 'Jabon para lavar platos'; aparece el botón X para borrar. | G12: La lista mostró únicamente Jabon para lavar platos y el botón X en el buscador. | H12: Captura de la búsqueda 'Jab' (11/10/2026) | I12: Aprobado | J12: Fernando, 11/10/2026
A13: PRU-08 | B13: Positiva | C13: RF-04 | D13: Buscar por categoría | E13: Texto de búsqueda: limpieza | F13: Se muestran los productos de la categoría 'Limpieza e higiene'. | G13: Con 'limpieza' se mostraron los productos de Limpieza e higiene. | H13: evidencias/PRU-08.png | I13: Aprobado | J13: Fernando, 11/10/2026
A14: PRU-09 | B14: Positiva | C14: RF-04 | D14: Búsqueda ignora tildes y mayúsculas | E14: Producto registrado: Azúcar 1lb | Texto de búsqueda: AZUCAR | F14: Se encuentra 'Azúcar 1lb'. | G14: Con 'AZUCAR' se encontró 'Azúcar 1lb'. | H14: evidencias/PRU-09.png | I14: Aprobado | J14: Fernando, 11/10/2026
A15: PRU-10 | B15: Positiva | C15: RF-04 | D15: Borrar la búsqueda con el botón X | E15: Escribir 'ace' y pulsar X | F15: El campo queda vacío y se muestra la lista completa. | G15: Con 'ace' se filtró la lista y al tocar la X volvió a mostrarse completa. | H15: evidencias/PRU-10.png | I15: Aprobado | J15: Fernando, 11/10/2026
A16: PRU-11 | B16: Positiva | C16: RF-05, RF-08 | D16: Editar el costo de un producto y recalcular el precio | E16: Jabon para lavar platos: costo 15.00 cambiado a 150.00 | F16: El formulario abre con los datos cargados y título 'Editar producto'; tras guardar, precio de venta 180,00 C$ y mensaje '¡Cambios guardados!'. | G16: El formulario abrió con los datos cargados; la lista mostró costo 150,00 C$, ganancia 30,00 C$ y precio 180,00 C$. | H16: Capturas del formulario 'Editar producto' y de la lista (11/10/2026) | I16: Aprobado | J16: Fernando, 11/10/2026
... A46: PRU-41 | B46: Usabilidad | C46: RNF-02 | D46: Legibilidad con el tamaño de fuente del sistema al máximo | E46: Configuración del teléfono: tamaño de fuente en el valor máximo | F46: No se cortan textos ni aparecen franjas de desbordamiento en la lista ni en el formulario. | G46: Con la fuente en el máximo no se cortaron textos ni hubo desbordamientos en la lista ni en el formulario. | H46: evidencias/PRU-41.png | I46: Aprobado | J46: Fernando, 11/10/2026

Sheet Resumen
A1: Resumen de ejecución de pruebas
A3: Estado | B3: Cantidad
A4: Aprobado | B4: =COUNTIF('Matriz de pruebas'!$I$6:$I$46,A4) -> 39
A5: Fallido | B5: =COUNTIF('Matriz de pruebas'!$I$6:$I$46,A5) -> 0
A6: Pendiente | B6: =COUNTIF('Matriz de pruebas'!$I$6:$I$46,A6) -> 0
A7: No aplica | B7: =COUNTIF('Matriz de pruebas'!$I$6:$I$46,A7) -> 2
A8: Total de pruebas | B8: =SUM(B4:B7) -> 41
A9: Pruebas aplicables (sin 'No aplica') | B9: =B8-B7 -> 39
A10: Pruebas ejecutadas (Aprobado + Fallido) | B10: =B4+B5 -> 39
A11: Porcentaje ejecutado | B11: =IF(B9=0,0,B10/B9) -> 1
A12: Porcentaje aprobado sobre lo ejecutado | B12: =IF(B10=0,0,B4/B10) -> 1
A14: Tipo de prueba | B14: Total | C14: Aprobadas | D14: Fallidas | E14: Pendientes
A15: Positiva | B15: =COUNTIF('Matriz de pruebas'!$B$6:$B$46,A15) -> 21 | C15: =COUNTIFS('Matriz de pruebas'!$B$6:$B$46,A15,'Matriz de pruebas'!$I$6:$I$46,"Aprobado") -> 21 | D15: =COUNTIFS('Matriz de pruebas'!$B$6:$B$46,A15,'Matriz de pruebas'!$I$6:$I$46,"Fallido") -> 0 | E15: =COUNTIFS('Matriz de pruebas'!$B$6:$B$46,A15,'Matriz de pruebas'!$I$6:$I$46,"Pendiente") -> 0
A16: Negativa | B16: =COUNTIF('Matriz de pruebas'!$B$6:$B$46,A16) -> 10 | C16: =COUNTIFS('Matriz de pruebas'!$B$6:$B$46,A16,'Matriz de pruebas'!$I$6:$I$46,"Aprobado") -> 10 | D16: =COUNTIFS('Matriz de pruebas'!$B$6:$B$46,A16,'Matriz de pruebas'!$I$6:$I$46,"Fallido") -> 0 | E16: =COUNTIFS('Matriz de pruebas'!$B$6:$B$46,A16,'Matriz de pruebas'!$I$6:$I$46,"Pendiente") -> 0
A17: Seguridad | B17: =COUNTIF('Matriz de pruebas'!$B$6:$B$46,A17) -> 5 | C17: =COUNTIFS('Matriz de pruebas'!$B$6:$B$46,A17,'Matriz de pruebas'!$I$6:$I$46,"Aprobado") -> 4 | D17: =COUNTIFS('Matriz de pruebas'!$B$6:$B$46,A17,'Matriz de pruebas'!$I$6:$I$46,"Fallido") -> 0 | E17: =COUNTIFS('Matriz de pruebas'!$B$6:$B$46,A17,'Matriz de pruebas'!$I$6:$I$46,"Pendiente") -> 0
A18: Conectividad | B18: =COUNTIF('Matriz de pruebas'!$B$6:$B$46,A18) -> 2 | C18: =COUNTIFS('Matriz de pruebas'!$B$6:$B$46,A18,'Matriz de pruebas'!$I$6:$I$46,"Aprobado") -> 1 | D18: =COUNTIFS('Matriz de pruebas'!$B$6:$B$46,A18,'Matriz de pruebas'!$I$6:$I$46,"Fallido") -> 0 | E18: =COUNTIFS('Matriz de pruebas'!$B$6:$B$46,A18,'Matriz de pruebas'!$I$6:$I$46,"Pendiente") -> 0
A19: Usabilidad | B19: =COUNTIF('Matriz de pruebas'!$B$6:$B$46,A19) -> 3 | C19: =COUNTIFS('Matriz de pruebas'!$B$6:$B$46,A19,'Matriz de pruebas'!$I$6:$I$46,"Aprobado") -> 3 | D19: =COUNTIFS('Matriz de pruebas'!$B$6:$B$46,A19,'Matriz de pruebas'!$I$6:$I$46,"Fallido") -> 0 | E19: =COUNTIFS('Matriz de pruebas'!$B$6:$B$46,A19,'Matriz de pruebas'!$I$6:$I$46,"Pendiente") -> 0
A21: Notas: (1) 'Aprobado' se registró según lo confirmado por el equipo tras ejecutar cada prueba; cada fila debe tener su evidencia en docs/evidencias/. (2) Los porcentajes se recalculan solos al cambiar el Estado en la hoja 'Matriz de pruebas'. (3) Según la guía de la sesión práctica, no se deben presentar mejoras que no se hayan medido.

Sheet Requisitos
A1: Trazabilidad: requisitos, módulos y pruebas
A3: ID | B3: Requisito | C3: Módulos / archivos | D3: Implementación | E3: N.º de pruebas | F3: Aprobadas
A4: RF-01 | B4: Listar el inventario con costo, ganancia y precio de venta | C4: inventario_screen.dart, producto_card.dart | D4: Implementado | E4: =COUNTIF('Matriz de pruebas'!$C$6:$C$46,"*"&A4&"*") -> 1 | F4: =COUNTIFS('Matriz de pruebas'!$C$6:$C$46,"*"&A4&"*",'Matriz de pruebas'!$I$6:$I$46,"Aprobado") -> 1
A5: RF-02 | B5: Agregar un producto (nombre, costo, categoría y stock) | C5: producto_form_screen.dart, InventarioViewModel.agregarProducto, ProductoRepositoryImpl.insertar | D5: Implementado | E5: =COUNTIF('Matriz de pruebas'!$C$6:$C$46,"*"&A5&"*") -> 4 | F5: =COUNTIFS('Matriz de pruebas'!$C$6:$C$46,"*"&A5&"*",'Matriz de pruebas'!$I$6:$I$46,"Aprobado") -> 4
A6: RF-03 | B6: Validar los datos con mensajes comprensibles | C6: producto_form_screen.dart (validadores); restricciones CHECK en SQLite (database_helper.dart) | D6: Implementado | E6: =COUNTIF('Matriz de pruebas'!$C$6:$C$46,"*"&A6&"*") -> 9 | F6: =COUNTIFS('Matriz de pruebas'!$C$6:$C$46,"*"&A6&"*",'Matriz de pruebas'!$I$6:$I$46,"Aprobado") -> 9
A7: RF-04 | B7: Buscar productos por nombre o categoría | C7: inventario_screen.dart | D7: Implementado | E7: =COUNTIF('Matriz de pruebas'!$C$6:$C$46,"*"&A7&"*") -> 5 | F7: =COUNTIFS('Matriz de pruebas'!$C$6:$C$46,"*"&A7&"*",'Matriz de pruebas'!$I$6:$I$46,"Aprobado") -> 5
A8: RF-05 | B8: Editar un producto existente | C8: producto_form_screen.dart, InventarioViewModel.actualizarProducto, ProductoRepositoryImpl.actualizar | D8: Implementado | E8: =COUNTIF('Matriz de pruebas'!$C$6:$C$46,"*"&A8&"*") -> 5 | F8: =COUNTIFS('Matriz de pruebas'!$C$6:$C$46,"*"&A8&"*",'Matriz de pruebas'!$I$6:$I$46,"Aprobado") -> 5
A9: RF-06 | B9: Eliminar un producto con confirmación | C9: inventario_screen.dart, InventarioViewModel.eliminarProducto, ProductoRepositoryImpl.eliminar | D9: Implementado | E9: =COUNTIF('Matriz de pruebas'!$C$6:$C$46,"*"&A9&"*") -> 2 | F9: =COUNTIFS('Matriz de pruebas'!$C$6:$C$46,"*"&A9&"*",'Matriz de pruebas'!$I$6:$I$46,"Aprobado") -> 2
A10: RF-07 | B10: Alerta de stock bajo (menor o igual a 5) y de producto agotado | C10: producto_card.dart, AppConstants.stockBajo | D10: Implementado | E10: =COUNTIF('Matriz de pruebas'!$C$6:$C$46,"*"&A10&"*") -> 5 | F10: =COUNTIFS('Matriz de pruebas'!$C$6:$C$46,"*"&A10&"*",'Matriz de pruebas'!$I$6:$I$46,"Aprobado") -> 5
A11: RF-08 | B11: Precio de venta = costo x 1.20 | C11: PricingService (domain/services) | D11: Implementado | E11: =COUNTIF('Matriz de pruebas'!$C$6:$C$46,"*"&A11&"*") -> 5 | F11: =COUNTIFS('Matriz de pruebas'!$C$6:$C$46,"*"&A11&"*",'Matriz de pruebas'!$I$6:$I$46,"Aprobado") -> 5
A12: RF-09 | B12: Roles de usuario y control de acceso | C12: (sin módulo todavía) | D12: No implementado | E12: =COUNTIF('Matriz de pruebas'!$C$6:$C$46,"*"&A12&"*") -> 1 | F12: =COUNTIFS('Matriz de pruebas'!$C$6:$C$46,"*"&A12&"*",'Matriz de pruebas'!$I$6:$I$46,"Aprobado") -> 0
A13: RF-10 | B13: Trazabilidad de operaciones (usuario, fecha, acción, resultado) | C13: (sin módulo todavía) | D13: No implementado | E13: =COUNTIF('Matriz de pruebas'!$C$6:$C$46,"*"&A13&"*") -> 0 | F13: =COUNTIFS('Matriz de pruebas'!$C$6:$C$46,"*"&A13&"*",'Matriz de pruebas'!$I$6:$I$46,"Aprobado") -> 0
A14: RNF-01 | B14: Funcionar sin conexión y conservar los datos | C14: DatabaseHelper (SQLite local) | D14: Implementado | E14: =COUNTIF('Matriz de pruebas'!$C$6:$C$46,"*"&A14&"*") -> 3 | F14: =COUNTIFS('Matriz de pruebas'!$C$6:$C$46,"*"&A14&"*",'Matriz de pruebas'!$I$6:$I$46,"Aprobado") -> 2
A15: RNF-02 | B15: Usabilidad para una persona adulta mayor (letra grande, botones de 48 dp o más) | C15: Capa presentation | D15: Implementado y verificado | E15: =COUNTIF('Matriz de pruebas'!$C$6:$C$46,"*"&A15&"*") -> 4 | F15: =COUNTIFS('Matriz de pruebas'!$C$6:$C$46,"*"&A15&"*",'Matriz de pruebas'!$I$6:$I$46,"Aprobado") -> 4
... A17: RNF-04 | B17: La interfaz no se desborda con valores grandes | C17: producto_card.dart | D17: Corregido y verificado | E17: =COUNTIF('Matriz de pruebas'!$C$6:$C$46,"*"&A17&"*") -> 1 | F17: =COUNTIFS('Matriz de pruebas'!$C$6:$C$46,"*"&A17&"*",'Matriz de pruebas'!$I$6:$I$46,"Aprobado") -> 1
A19: Nota: el conteo busca el ID del requisito dentro de la columna 'Requisito' de la matriz; una prueba que cubre varios requisitos se cuenta en cada uno.

Sheet Defectos y pendientes
A1: Defectos, decisiones de corrección y trabajo pendiente
A3: ID | B3: Descripción | C3: Cómo se detectó | D3: Severidad | E3: Decisión de corrección | F3: Estado
A4: DEF-01 | B4: Desbordamiento de 3,4 px en la caja 'PRECIO DE VENTA' con un precio de 180,00 C$. | C4: Emulador, 11/10/2026 (franja amarilla y negra) | D4: Media | E4: Se envolvió el precio en Expanded + FittedBox (scaleDown) en producto_card.dart. | F4: Corregido y verificado (PRU-21 y PRU-41)
A5: DEF-02 | B5: Al editar, el costo se muestra como 150.0 en lugar de 150.00. | C5: Emulador, 11/10/2026 | D5: Baja | E5: Usar toStringAsFixed(2) al cargar el costo en initState de producto_form_screen.dart. | F5: Pendiente
A6: DEF-03 | B6: La prueba test/widget_test.dart falla: busca una clase MyApp que no existe. | C6: VS Code, pestaña Problemas | D6: Baja (no afecta la app) | E6: Borrar el archivo o reemplazarlo por pruebas reales del proyecto. | F6: Pendiente
A7: DEF-04 | B7: Aviso de API obsoleta: 'value' en DropdownButtonFormField (usar initialValue). | C7: VS Code, pestaña Problemas | D7: Muy baja | E7: Cambiar value por initialValue en producto_form_screen.dart. | F7: Pendiente
A8: DEF-05 | B8: El negocio aparece como 'Tulita' en la app y como 'Nachita' en parte del documento del proyecto. | C8: Revisión de documentos y de la app | D8: Media (consistencia) | E8: El equipo debe elegir un solo nombre y corregirlo en AppConstants.appName, README y documento. | F8: Pendiente de decisión
A9: DEF-06 | B9: No existen roles de usuario ni control de acceso (la guía exige al menos dos roles). | C9: Revisión contra la guía de la sesión práctica | D9: Alta (requisito) | E9: Diseñar e implementar inicio de sesión con roles (por ejemplo, administradora y supervisor). | F9: Pendiente
A10: DEF-07 | B10: No se registra la trazabilidad de operaciones (usuario, fecha, acción, resultado). | C10: Revisión contra la guía de la sesión práctica | D10: Alta (requisito) | E10: Agregar una tabla de eventos en SQLite y registrar agregar, editar y eliminar. | F10: Pendiente
A11: DEF-08 | B11: No hay pruebas automatizadas del proyecto. | C11: Revisión del repositorio | D11: Media | E11: Escribir pruebas unitarias de PricingService y del ViewModel. | F11: Pendiente
